calculator_179d/SurrogateModelMetricConversion.py
calculator_179d/__init__.py
calculator_179d/calculate_common_features.py
calculator_179d/constants.py
calculator_179d/data_types.py
calculator_179d/main_calculator.py
calculator_179d/output_data_types.py
calculator_179d/surrogate_model.py
calculator_179d/waterheater_attributes.py
calculator_179d/model_files/baseline_electricity_retail_stripmall_PSZ-AC_with_electric_coil_CZ1A.pk
calculator_179d/model_files/baseline_electricity_retail_stripmall_PSZ-AC_with_electric_coil_CZ2A.pk
calculator_179d/model_files/baseline_electricity_retail_stripmall_PSZ-AC_with_electric_coil_CZ2B.pk
calculator_179d/model_files/baseline_electricity_retail_stripmall_PSZ-AC_with_electric_coil_CZ3A.pk
calculator_179d/model_files/baseline_electricity_retail_stripmall_PSZ-AC_with_electric_coil_CZ3B.pk
calculator_179d/model_files/baseline_electricity_retail_stripmall_PSZ-AC_with_electric_coil_CZ3C.pk
calculator_179d/model_files/baseline_electricity_retail_stripmall_PSZ-AC_with_electric_coil_CZ4A.pk
calculator_179d/model_files/baseline_electricity_retail_stripmall_PSZ-AC_with_electric_coil_CZ4B.pk
calculator_179d/model_files/baseline_electricity_retail_stripmall_PSZ-AC_with_electric_coil_CZ4C.pk
calculator_179d/model_files/baseline_electricity_retail_stripmall_PSZ-AC_with_electric_coil_CZ5A.pk
calculator_179d/model_files/baseline_electricity_retail_stripmall_PSZ-AC_with_electric_coil_CZ5B.pk
calculator_179d/model_files/baseline_electricity_retail_stripmall_PSZ-AC_with_electric_coil_CZ5C.pk
calculator_179d/model_files/baseline_electricity_retail_stripmall_PSZ-AC_with_electric_coil_CZ6A.pk
calculator_179d/model_files/baseline_electricity_retail_stripmall_PSZ-AC_with_electric_coil_CZ6B.pk
calculator_179d/model_files/baseline_electricity_retail_stripmall_PSZ-AC_with_electric_coil_CZ7.pk
calculator_179d/model_files/baseline_electricity_retail_stripmall_PSZ-AC_with_electric_coil_CZ8.pk
BEM_prediction_models-2.0.0.dist-info/LICENSE.md
BEM_prediction_models-2.0.0.dist-info/METADATA
BEM_prediction_models-2.0.0.dist-info/WHEEL
BEM_prediction_models-2.0.0.dist-info/top_level.txt
BEM_prediction_models-2.0.0.dist-info/RECORD
