Metadata-Version: 2.2
Name: BEM-prediction-models
Version: 2.0.0
Summary: package implementing BEM prediction models
Home-page: https://github.com/NREL/BEM-prediction-models/
Author: vchinde, Alex Chapin, rchintala13
Author-email: venkatesh.chinde@nrel.gov
Maintainer: NREL
Maintainer-email: venkatesh.chinde@nrel.gov
Keywords: prediction models
Classifier: Development Status :: 4 - Beta
Classifier: Intended Audience :: Developers
Classifier: Operating System :: OS Independent
Classifier: Programming Language :: Python :: 3.9
License-File: LICENSE.md
Requires-Dist: numpy==1.24.4
Requires-Dist: scikit-learn==1.2.2
Requires-Dist: strenum
Requires-Dist: pydantic~=2.10
Provides-Extra: dev
Requires-Dist: pytest~=8.3; extra == "dev"
Requires-Dist: black~=24.8; extra == "dev"
Requires-Dist: isort~=5.13; extra == "dev"
Requires-Dist: pre-commit; extra == "dev"
Requires-Dist: mypy; extra == "dev"
Requires-Dist: pytest-cov; extra == "dev"
Requires-Dist: flake8; extra == "dev"
Requires-Dist: pandas[excel]~=2.0; extra == "dev"
Requires-Dist: bump-my-version; extra == "dev"
Requires-Dist: joblib-stubs; extra == "dev"
Requires-Dist: pandas-stubs; extra == "dev"
Provides-Extra: docs
Requires-Dist: Sphinx~=7.1; extra == "docs"
Requires-Dist: autodoc_pydantic[erdantic]; extra == "docs"
Requires-Dist: sphinx-rtd-theme; extra == "docs"
Requires-Dist: rst2pdf; extra == "docs"
